ta4/__init__.py
ta4/analyzer.py
ta4/diff.py
ta4/placeholder.py
ta4/sentence.py
ta4/text.py
ta4/utils.py
ta4/data/nltk/english.pickle
ta4-0.3.35.dist-info/METADATA
ta4-0.3.35.dist-info/WHEEL
ta4-0.3.35.dist-info/top_level.txt
ta4-0.3.35.dist-info/RECORD
