Metadata-Version: 2.1
Name: ta4
Version: 0.3.35
Summary: UNKNOWN
Home-page: https://github.com/KokocGroup/ta4
Author: UNKNOWN
Author-email: UNKNOWN
License: UNKNOWN
Download-URL: https://github.com/KokocGroup/ta4/tarball/v0.3.35
Platform: UNKNOWN
Requires-Dist: nltk (==3.0.0)
Requires-Dist: pymorphy2 (==0.8)
Requires-Dist: lxml (==3.4.4)
Requires-Dist: beautifulsoup4 (==4.3.2)
